robustcheck/RobustnessCheck.py
robustcheck/__init__.py
robustcheck/config.py
robustcheck/EpsilonGreedyUntargeted/EpsilonGreedyUntargeted.py
robustcheck/EpsilonGreedyUntargeted/__init__.py
robustcheck/EpsilonGreedyUntargeted/utils.py
robustcheck/EvoStrategyUniformUntargeted/EvoStrategyUniformUntargeted.py
robustcheck/EvoStrategyUniformUntargeted/__init__.py
robustcheck/SimBA/SimBA.py
robustcheck/SimBA/__init__.py
robustcheck/types/AttackType.py
robustcheck/types/EvoStrategy.py
robustcheck/types/UntargetedAttack.py
robustcheck/types/__init__.py
robustcheck/utils/__init__.py
robustcheck/utils/metrics.py
robustcheck/utils/utils.py
robustcheck-1.1.0.dist-info/LICENSE.txt
robustcheck-1.1.0.dist-info/METADATA
robustcheck-1.1.0.dist-info/WHEEL
robustcheck-1.1.0.dist-info/top_level.txt
robustcheck-1.1.0.dist-info/RECORD
